funapi/__init__.py
funcore-0.0.1.dist-info/LICENSE
funcore-0.0.1.dist-info/METADATA
funcore-0.0.1.dist-info/WHEEL
funcore-0.0.1.dist-info/entry_points.txt
funcore-0.0.1.dist-info/top_level.txt
funcore-0.0.1.dist-info/RECORD
