Metadata-Version: 2.1
Name: funcore
Version: 0.0.1
Summary: funcore
Home-page: https://github.com/farfarfun/funcore
Author: bingtao
Author-email: 1007530194@qq.com
License-File: LICENSE
Requires-Dist: funpypi
Requires-Dist: funfile
Requires-Dist: requests
Requires-Dist: tqdm
